ckanext/__init__.py
ckanext/check_link/__init__.py
ckanext/check_link/cli.py
ckanext/check_link/helpers.py
ckanext/check_link/plugin.py
ckanext/check_link/views.py
ckanext/check_link/assets/script.js
ckanext/check_link/assets/style.css
ckanext/check_link/assets/webassets.yml
ckanext/check_link/implementations/__init__.py
ckanext/check_link/implementations/collection.py
ckanext/check_link/logic/__init__.py
ckanext/check_link/logic/auth.py
ckanext/check_link/logic/schema.py
ckanext/check_link/logic/action/__init__.py
ckanext/check_link/logic/action/check.py
ckanext/check_link/logic/action/report.py
ckanext/check_link/migration/check_link/alembic.ini
ckanext/check_link/migration/check_link/env.py
ckanext/check_link/migration/check_link/script.py.mako
ckanext/check_link/migration/check_link/versions/001_564f2016af51_create_report_table.py
ckanext/check_link/migration/check_link/versions/002_dad15b4f251a_add_ondelete_cascade_to_resource_id.py
ckanext/check_link/model/__init__.py
ckanext/check_link/model/base.py
ckanext/check_link/model/report.py
ckanext/check_link/templates/header.html
ckanext/check_link/templates/check_link/base.html
ckanext/check_link/templates/check_link/base_admin.html
ckanext/check_link/templates/check_link/global_report.html
ckanext/check_link/templates/check_link/organization_report.html
ckanext/check_link/templates/check_link/package_report.html
ckanext/check_link/templates/check_link/snippets/collection_main.html
ckanext/check_link/templates/check_link/snippets/collection_pager.html
ckanext/check_link/templates/check_link/snippets/collection_record.html
ckanext/check_link/templates/check_link/snippets/report_item.html
ckanext/check_link/tests/__init__.py
ckanext/check_link/tests/conftest.py
ckanext/check_link/tests/test_plugin.py
ckanext/check_link/tests/logic/__init__.py
ckanext/check_link/tests/logic/action/__init__.py
ckanext/check_link/tests/logic/action/test_check.py
ckanext/check_link/tests/logic/action/test_report.py
ckanext_check_link-0.2.2.dist-info/LICENSE
ckanext_check_link-0.2.2.dist-info/METADATA
ckanext_check_link-0.2.2.dist-info/WHEEL
ckanext_check_link-0.2.2.dist-info/entry_points.txt
ckanext_check_link-0.2.2.dist-info/top_level.txt
ckanext_check_link-0.2.2.dist-info/RECORD
