Metadata-Version: 2.1
Name: ckanext-check-link
Version: 0.2.2
Summary: Resource URL checker
Author-email: DataShades <datashades@linkdigital.com.au>, Sergey Motornyuk <sergey.motornyuk@linkdigital.com.au>
Maintainer-email: DataShades <datashades@linkdigital.com.au>
License: AGPL
Project-URL: Homepage, https://github.com/DataShades/ckanext-check-link
Keywords: CKAN
Classifier: Development Status :: 4 - Beta
Classifier: License :: OSI Approved :: GNU Affero General Public License v3 or later (AGPLv3+)
Classifier: Programming Language :: Python :: 3.8
Classifier: Programming Language :: Python :: 3.9
Classifier: Programming Language :: Python :: 3.10
Classifier: Programming Language :: Python :: 3.11
License-File: LICENSE
Requires-Dist: check-link ~=0.0.11
Requires-Dist: typing-extensions
Requires-Dist: ckanext-toolbelt
Requires-Dist: ckanext-collection
Provides-Extra: dev
Requires-Dist: pytest-ckan ; extra == 'dev'
Requires-Dist: pytest-factoryboy ; extra == 'dev'
Requires-Dist: responses ; extra == 'dev'
Requires-Dist: pytest-httpx ; extra == 'dev'
Requires-Dist: pytest-asyncio ; extra == 'dev'
